fadeit/__init__.py
fadeit/fadeit.py
fadeit-1.0.0.dist-info/LICENSE
fadeit-1.0.0.dist-info/METADATA
fadeit-1.0.0.dist-info/WHEEL
fadeit-1.0.0.dist-info/top_level.txt
fadeit-1.0.0.dist-info/RECORD
